nonebot_plugin_hikarisearch/__init__.py
nonebot_plugin_hikarisearch/config.py
nonebot_plugin_hikarisearch/data_source.py
nonebot_plugin_hikarisearch-0.1.7.dist-info/LICENSE
nonebot_plugin_hikarisearch-0.1.7.dist-info/WHEEL
nonebot_plugin_hikarisearch-0.1.7.dist-info/METADATA
nonebot_plugin_hikarisearch-0.1.7.dist-info/RECORD
