Metadata-Version: 2.1
Name: nonebot-plugin-hikarisearch
Version: 0.1.7
Summary: 基于 HikariSearch 的又一个 Nonebot2 搜图插件
Home-page: https://github.com/noneplugin/nonebot-plugin-hikarisearch
License: MIT
Author: meetwq
Author-email: meetwq@gmail.com
Requires-Python: >=3.8,<4.0
Classifier: License :: OSI Approved :: MIT License
Classifier: Programming Language :: Python :: 3
Classifier: Programming Language :: Python :: 3.10
Classifier: Programming Language :: Python :: 3.8
Classifier: Programming Language :: Python :: 3.9
Requires-Dist: httpx (>=0.19.0)
Requires-Dist: nonebot-adapter-onebot (>=2.0.0-beta.1,<3.0.0)
Requires-Dist: nonebot2 (>=2.0.0-beta.4,<3.0.0)
Project-URL: Repository, https://github.com/noneplugin/nonebot-plugin-hikarisearch
